nlScript_mic_lang/__init__.py
nlScript_mic_lang/interpolator.py
nlScript_mic_lang/languagecontrol.py
nlScript_mic_lang/main.py
nlScript_mic_lang/microscope.py
nlScript_mic_lang/timeline.py
nlScript_microscope_language-0.3.0.dist-info/LICENSE.txt
nlScript_microscope_language-0.3.0.dist-info/METADATA
nlScript_microscope_language-0.3.0.dist-info/WHEEL
nlScript_microscope_language-0.3.0.dist-info/entry_points.txt
nlScript_microscope_language-0.3.0.dist-info/top_level.txt
nlScript_microscope_language-0.3.0.dist-info/RECORD
